draftable/__init__.py
draftable/client.py
draftable/commands/__init__.py
draftable/commands/dr_compare.py
draftable/endpoints/__init__.py
draftable/endpoints/exceptions.py
draftable/endpoints/validation.py
draftable/endpoints/comparisons/__init__.py
draftable/endpoints/comparisons/changes.py
draftable/endpoints/comparisons/comparison.py
draftable/endpoints/comparisons/comparisons.py
draftable/endpoints/comparisons/identifier.py
draftable/endpoints/comparisons/sides.py
draftable/endpoints/comparisons/signing.py
draftable/endpoints/exports/__init__.py
draftable/endpoints/exports/export.py
draftable/endpoints/exports/exports.py
draftable/transport/__init__.py
draftable/transport/rest_client.py
draftable/utilities/__init__.py
draftable/utilities/timestamp.py
draftable/utilities/urls.py
draftable_compare_api-1.4.3.dist-info/LICENSE
draftable_compare_api-1.4.3.dist-info/METADATA
draftable_compare_api-1.4.3.dist-info/WHEEL
draftable_compare_api-1.4.3.dist-info/entry_points.txt
draftable_compare_api-1.4.3.dist-info/top_level.txt
draftable_compare_api-1.4.3.dist-info/zip-safe
draftable_compare_api-1.4.3.dist-info/RECORD
