Metadata-Version: 2.1
Name: draftable-compare-api
Version: 1.4.3
Summary: Client library for the Draftable document comparison API
Home-page: https://github.com/draftable/compare-api-python-client
Author: Draftable
Author-email: contact@draftable.com
Maintainer: Draftable
Maintainer-email: contact@draftable.com
License: MIT
Project-URL: Changelog, https://github.com/draftable/compare-api-python-client/blob/stable/CHANGELOG.md
Project-URL: Documentation, https://github.com/draftable/compare-api-python-client/blob/stable/README.md
Project-URL: Source, https://github.com/draftable/compare-api-python-client
Project-URL: Tracker, https://github.com/draftable/compare-api-python-client/issues
Keywords: draftable,api,compare,comparison,comparisons,pdf,word,document,documents,doc,docx,powerpoint,presentation,presentations,ppt,pptx
Classifier: Development Status :: 5 - Production/Stable
Classifier: Intended Audience :: Developers
Classifier: License :: OSI Approved :: MIT License
Classifier: Natural Language :: English
Classifier: Programming Language :: Python
Classifier: Programming Language :: Python :: 3
Classifier: Programming Language :: Python :: 3.8
Classifier: Programming Language :: Python :: 3.9
Classifier: Programming Language :: Python :: 3.10
Classifier: Programming Language :: Python :: 3.11
Classifier: Programming Language :: Python :: 3.12
Classifier: Programming Language :: Python :: 3.13
Classifier: Topic :: Software Development :: Libraries
Requires-Python: <4,>=3.7
License-File: LICENSE
Requires-Dist: requests
Provides-Extra: dev
Requires-Dist: black>=21.12b0; extra == "dev"
Requires-Dist: check-manifest; extra == "dev"
Requires-Dist: coverage[toml]; extra == "dev"
Requires-Dist: flake8; extra == "dev"
Requires-Dist: Flake8-pyproject; extra == "dev"
Requires-Dist: isort; extra == "dev"
Requires-Dist: mypy; extra == "dev"
Requires-Dist: pylint; extra == "dev"
Requires-Dist: pytest; extra == "dev"
Requires-Dist: pytest-cov; extra == "dev"
Requires-Dist: tox>=3.3.0; extra == "dev"
Requires-Dist: twine; extra == "dev"
Requires-Dist: types-requests; extra == "dev"
Requires-Dist: wheel; extra == "dev"
